hc128.py
HC128_Cipher-1.0.1.dist-info/METADATA
HC128_Cipher-1.0.1.dist-info/WHEEL
HC128_Cipher-1.0.1.dist-info/top_level.txt
HC128_Cipher-1.0.1.dist-info/RECORD
