Metadata-Version: 2.1
Name: HC128-Cipher
Version: 1.0.1
Summary: Python implementation of HC-128 stream cipher
Requires-Python: >=3.10
